{"version":1,"resource":"file:///Users/ryanatk/www/jouzen/ourafront/components/pages/business/data/logo.ts","entries":[{"id":"RISH.ts","timestamp":1666965625297},{"id":"Mxc1.ts","timestamp":1666965654956},{"id":"6ar3.ts","timestamp":1666965715361},{"id":"8gZ3.ts","timestamp":1666965854130},{"id":"8MZr.ts","timestamp":1666965888815},{"id":"jstO.ts","timestamp":1666966351055},{"id":"n4fA.ts","timestamp":1666967202348},{"id":"pwMv.ts","timestamp":1666967309583},{"id":"uu9V.ts","timestamp":1666967394299},{"id":"1c7X.ts","timestamp":1666967534077},{"id":"B0nw.ts","timestamp":1666967662926},{"id":"YuO6.ts","timestamp":1666968129173},{"id":"v44x.ts","timestamp":1666968139553},{"id":"TTtJ.ts","timestamp":1666968228883},{"id":"h2OV.ts","timestamp":1666968280831},{"id":"Qn0e.ts","timestamp":1666968393008},{"id":"ui1w.ts","timestamp":1666968945838},{"id":"sBwY.ts","timestamp":1666969070398},{"id":"mbN3.ts","timestamp":1666969102645},{"id":"mY6k.ts","timestamp":1666969634295},{"id":"hFwj.ts","timestamp":1666969808372},{"id":"RA7k.ts","timestamp":1666970049337},{"id":"0c69.ts","timestamp":1666970098821},{"id":"eESW.ts","timestamp":1666972043466},{"id":"FKNS.ts","timestamp":1666972283332},{"id":"rf5c.ts","timestamp":1666972311602},{"id":"yUTL.ts","timestamp":1666972322964},{"id":"IST3.ts","timestamp":1666972352948},{"id":"d7IE.ts","timestamp":1666972364267},{"id":"jNMl.ts","timestamp":1666972391933},{"id":"1czl.ts","timestamp":1666972408204},{"id":"ijLL.ts","timestamp":1666973743055},{"id":"thde.ts","timestamp":1667233995530},{"id":"35ZX.ts","timestamp":1667240334382},{"id":"uMm1.ts","timestamp":1667240353890},{"id":"NdY3.ts","timestamp":1667240420708},{"id":"Q29x.ts","timestamp":1667240438347},{"id":"MmxA.ts","timestamp":1667240452102},{"id":"9wOG.ts","timestamp":1667240812185},{"id":"zaRk.ts","timestamp":1668641555028},{"id":"aHux.ts","timestamp":1668642253260},{"id":"YT8I.ts","timestamp":1668642320877},{"id":"Xodf.ts","timestamp":1668643780687},{"id":"HFFP.ts","timestamp":1668643824466},{"id":"TPfM.ts","timestamp":1668644015145},{"id":"FMUm.ts","timestamp":1668644033405},{"id":"EGWY.ts","timestamp":1668707781267}]}