{"version":1,"resource":"file:///Users/ryanatk/www/jouzen/ourafront/config/presetFeatureFlags.js","entries":[{"id":"uyHL.js","timestamp":1668460626073},{"id":"9KzO.js","timestamp":1668468249891},{"id":"4oay.js","timestamp":1668468688641},{"id":"LsAj.js","timestamp":1668635702003},{"id":"J356.js","timestamp":1668635882477},{"id":"SJMx.js","timestamp":1668636463245},{"id":"IqHX.js","timestamp":1668636515299},{"id":"VeAF.js","timestamp":1668636550698},{"id":"TywQ.js","timestamp":1668637166657},{"id":"Ne5F.js","timestamp":1668637672437},{"id":"NovM.js","timestamp":1670018165184},{"id":"zf1L.js","timestamp":1671222997562},{"id":"6Sg3.js","timestamp":1671553084503},{"id":"OKSB.js","timestamp":1671553107945},{"id":"xx2x.js","timestamp":1671555209226},{"id":"MRqM.js","timestamp":1671574746891},{"id":"xIiR.js","timestamp":1671635703036},{"id":"UQU3.js","timestamp":1672872720758},{"id":"fq2L.js","timestamp":1672964259981},{"id":"Pqsf.js","timestamp":1674675193696},{"id":"CRk4.js","timestamp":1674693997381},{"id":"wLDn.js","timestamp":1674746675500},{"id":"Iec3.js","timestamp":1674747732754},{"id":"x2hm.js","timestamp":1674749124176},{"id":"QHi0.js","timestamp":1674749267112},{"id":"4JP0.js","timestamp":1674749316453},{"id":"Gp5D.js","timestamp":1674749548709},{"id":"aoxe.js","timestamp":1674751529027},{"id":"suJT.js","source":"undoRedo.source","timestamp":1674751561724},{"id":"5LWM.js","timestamp":1674751580614},{"id":"CjOK.js","timestamp":1674751604856},{"id":"ScGA.js","timestamp":1674751720656},{"id":"ePyh.js","timestamp":1674751732819},{"id":"Iwbb.js","timestamp":1674751748124},{"id":"hWDh.js","timestamp":1674755428819},{"id":"hNfx.js","timestamp":1674756122123},{"id":"l1jr.js","timestamp":1674767314466},{"id":"yfWr.js","timestamp":1674767518555},{"id":"xbfG.js","timestamp":1674767565840},{"id":"MUTU.js","timestamp":1674767735255},{"id":"cEi0.js","timestamp":1674767751876},{"id":"Bt6t.js","timestamp":1674767767137},{"id":"sc6k.js","timestamp":1674767990562},{"id":"Brv6.js","timestamp":1674768011644},{"id":"wjBT.js","timestamp":1674768029193},{"id":"g8k5.js","timestamp":1674768049904},{"id":"GAmY.js","timestamp":1674774501407},{"id":"uIl2.js","timestamp":1674774548040},{"id":"byaF.js","timestamp":1674774574127},{"id":"6jCj.js","timestamp":1674774610511}]}