{"version":1,"resource":"file:///Users/ryanatk/www/OnlineOrdering/OnlineOrdering/ClientApp/src/common/utils/date/date.js","entries":[{"id":"cc1l.js","timestamp":1650460952861},{"id":"3tZW.js","timestamp":1650460969789},{"id":"pZAS.js","timestamp":1650460992722},{"id":"z3Ue.js","timestamp":1650461027940},{"id":"f2Og.js","timestamp":1650461128001},{"id":"BPFu.js","timestamp":1650461183967},{"id":"hYFc.js","timestamp":1650462353647},{"id":"60tj.js","timestamp":1650462396762},{"id":"qnas.js","timestamp":1650462583658},{"id":"V1l1.js","timestamp":1650462796853},{"id":"SJCr.js","timestamp":1650462812511},{"id":"7z8q.js","timestamp":1650462833838},{"id":"zTFC.js","timestamp":1650462945912},{"id":"R98G.js","timestamp":1650462960167},{"id":"zDeb.js","timestamp":1650462983412},{"id":"3o6D.js","timestamp":1650463332910},{"id":"waVg.js","timestamp":1650463582002},{"id":"Lbtg.js","timestamp":1650466709904},{"id":"bkWy.js","timestamp":1650466836860},{"id":"81Xs.js","timestamp":1650466907045},{"id":"qIzc.js","timestamp":1650467216392},{"id":"Hh2L.js","timestamp":1650467244508},{"id":"YKT8.js","timestamp":1650467279172},{"id":"X8Lk.js","timestamp":1650467289240},{"id":"iuvK.js","timestamp":1650467317126},{"id":"K63d.js","timestamp":1650467333738},{"id":"iEKR.js","timestamp":1650467362832},{"id":"sxlR.js","timestamp":1650467403486},{"id":"HSRw.js","timestamp":1650467417369},{"id":"pgRR.js","timestamp":1650467482917},{"id":"rao3.js","timestamp":1650467506096},{"id":"gQWE.js","timestamp":1650467523706},{"id":"V4bJ.js","timestamp":1650467645341},{"id":"mrdq.js","timestamp":1650468149960},{"id":"WIfj.js","timestamp":1650468195173},{"id":"pLlO.js","timestamp":1650468210487},{"id":"BVsC.js","timestamp":1650468252594},{"id":"hZlK.js","timestamp":1650468278938},{"id":"U5Ew.js","timestamp":1650468395967},{"id":"Iz8R.js","timestamp":1650468413325},{"id":"2FI3.js","timestamp":1650468436355},{"id":"gkJA.js","timestamp":1650468465307},{"id":"SyGI.js","timestamp":1650468483835},{"id":"ChiK.js","timestamp":1650468511312},{"id":"Jz4W.js","timestamp":1650468600518},{"id":"yklQ.js","timestamp":1650468616797},{"id":"y5I8.js","timestamp":1650468641681},{"id":"u04S.js","timestamp":1650468862853},{"id":"6gqY.js","timestamp":1650476202093},{"id":"kUnA.js","timestamp":1650476355679}]}