{"version":1,"resource":"file:///Users/ryanatk/www/jouzen/ourafront/tailwind.config.js","entries":[{"id":"jfWD.js","timestamp":1657304619976},{"id":"RVSd.js","timestamp":1657304763259},{"id":"ibjF.js","timestamp":1657833160391},{"id":"O8vx.js","timestamp":1660089931692},{"id":"cioL.js","timestamp":1660090075023},{"id":"je6h.js","timestamp":1660090890417},{"id":"t9yH.js","timestamp":1660090916177},{"id":"m7Fb.js","timestamp":1660175613762},{"id":"WpoM.js","timestamp":1660248615958},{"id":"W8fO.js","timestamp":1660249019382},{"id":"7WuH.js","timestamp":1660249359659},{"id":"6YDk.js","timestamp":1660249443363},{"id":"mEM6.js","timestamp":1660759073342},{"id":"HfGK.js","timestamp":1660759221259},{"id":"rNjW.js","timestamp":1661280329682},{"id":"NcW5.js","timestamp":1661979217652},{"id":"crTU.js","timestamp":1661979272403},{"id":"1BPe.js","timestamp":1661979335221},{"id":"yfvu.js","timestamp":1661980103588},{"id":"oAii.js","timestamp":1661980131715},{"id":"94AA.js","timestamp":1662070535964},{"id":"JBmN.js","timestamp":1662071581893},{"id":"3QzM.js","timestamp":1663177549002},{"id":"annC.js","timestamp":1663184797963},{"id":"Fvcg.js","timestamp":1663184813852},{"id":"LAe7.js","timestamp":1665169344751},{"id":"n4T1.js","timestamp":1665169414104},{"id":"tzi5.js","timestamp":1665169704935},{"id":"VxJg.js","timestamp":1673390932557},{"id":"Eenc.js","timestamp":1673391364082}]}